<?xml version="1.0" encoding="UTF-8" standalone="no"?><entities>
	<entity>
		<entity-name>ee.ttu.catering.rest.model.User</entity-name>
		<entity-width>120</entity-width>
		<entity-height>110</entity-height>
		<entity-X-Coordinate>500</entity-X-Coordinate>
		<entity-Y-Coordinate>30</entity-Y-Coordinate>
		<primary-collapsed>false</primary-collapsed>
		<relation-collapsed>false</relation-collapsed>
		<basic-collapsed>false</basic-collapsed>
	</entity>

	<entity>
		<entity-name>ee.ttu.catering.rest.model.DinerComment</entity-name>
		<entity-width>120</entity-width>
		<entity-height>70</entity-height>
		<entity-X-Coordinate>349</entity-X-Coordinate>
		<entity-Y-Coordinate>281</entity-Y-Coordinate>
		<primary-collapsed>false</primary-collapsed>
		<relation-collapsed>false</relation-collapsed>
		<basic-collapsed>false</basic-collapsed>
	</entity>

	<entity>
		<entity-name>ee.ttu.catering.rest.model.MenuComment</entity-name>
		<entity-width>120</entity-width>
		<entity-height>70</entity-height>
		<entity-X-Coordinate>349</entity-X-Coordinate>
		<entity-Y-Coordinate>435</entity-Y-Coordinate>
		<primary-collapsed>false</primary-collapsed>
		<relation-collapsed>false</relation-collapsed>
		<basic-collapsed>false</basic-collapsed>
	</entity>

	<entity>
		<entity-name>ee.ttu.catering.rest.model.base.IdEntity</entity-name>
		<entity-width>120</entity-width>
		<entity-height>30</entity-height>
		<entity-X-Coordinate>10</entity-X-Coordinate>
		<entity-Y-Coordinate>321</entity-Y-Coordinate>
		<primary-collapsed>false</primary-collapsed>
		<relation-collapsed>false</relation-collapsed>
		<basic-collapsed>false</basic-collapsed>
	</entity>

	<entity>
		<entity-name>ee.ttu.catering.rest.model.MenuItem</entity-name>
		<entity-width>120</entity-width>
		<entity-height>168</entity-height>
		<entity-X-Coordinate>10</entity-X-Coordinate>
		<entity-Y-Coordinate>429</entity-Y-Coordinate>
		<primary-collapsed>false</primary-collapsed>
		<relation-collapsed>false</relation-collapsed>
		<basic-collapsed>false</basic-collapsed>
	</entity>

	<entity>
		<entity-name>ee.ttu.catering.rest.model.base.CommentEntity</entity-name>
		<entity-width>120</entity-width>
		<entity-height>90</entity-height>
		<entity-X-Coordinate>500</entity-X-Coordinate>
		<entity-Y-Coordinate>346</entity-Y-Coordinate>
		<primary-collapsed>false</primary-collapsed>
		<relation-collapsed>false</relation-collapsed>
		<basic-collapsed>false</basic-collapsed>
	</entity>

	<entity>
		<entity-name>ee.ttu.catering.rest.model.Diner</entity-name>
		<entity-width>120</entity-width>
		<entity-height>248</entity-height>
		<entity-X-Coordinate>181</entity-X-Coordinate>
		<entity-Y-Coordinate>28</entity-Y-Coordinate>
		<primary-collapsed>false</primary-collapsed>
		<relation-collapsed>false</relation-collapsed>
		<basic-collapsed>false</basic-collapsed>
	</entity>

	<entity>
		<entity-name>ee.ttu.catering.rest.model.base.LikeEntity</entity-name>
		<entity-width>120</entity-width>
		<entity-height>90</entity-height>
		<entity-X-Coordinate>10</entity-X-Coordinate>
		<entity-Y-Coordinate>122</entity-Y-Coordinate>
		<primary-collapsed>false</primary-collapsed>
		<relation-collapsed>false</relation-collapsed>
		<basic-collapsed>false</basic-collapsed>
	</entity>

	<entity>
		<entity-name>ee.ttu.catering.rest.model.Menu</entity-name>
		<entity-width>120</entity-width>
		<entity-height>188</entity-height>
		<entity-X-Coordinate>181</entity-X-Coordinate>
		<entity-Y-Coordinate>376</entity-Y-Coordinate>
		<primary-collapsed>false</primary-collapsed>
		<relation-collapsed>false</relation-collapsed>
		<basic-collapsed>false</basic-collapsed>
	</entity>

	<entity>
		<entity-name>ee.ttu.catering.rest.model.DinerLike</entity-name>
		<entity-width>120</entity-width>
		<entity-height>70</entity-height>
		<entity-X-Coordinate>10</entity-X-Coordinate>
		<entity-Y-Coordinate>28</entity-Y-Coordinate>
		<primary-collapsed>false</primary-collapsed>
		<relation-collapsed>false</relation-collapsed>
		<basic-collapsed>false</basic-collapsed>
	</entity>

	<entity>
		<entity-name>ee.ttu.catering.rest.model.Image</entity-name>
		<entity-width>120</entity-width>
		<entity-height>166</entity-height>
		<entity-X-Coordinate>343</entity-X-Coordinate>
		<entity-Y-Coordinate>28</entity-Y-Coordinate>
		<primary-collapsed>false</primary-collapsed>
		<relation-collapsed>false</relation-collapsed>
		<basic-collapsed>false</basic-collapsed>
	</entity>

	<entity>
		<entity-name>ee.ttu.catering.rest.model.Token</entity-name>
		<entity-width>120</entity-width>
		<entity-height>128</entity-height>
		<entity-X-Coordinate>500</entity-X-Coordinate>
		<entity-Y-Coordinate>170</entity-Y-Coordinate>
		<primary-collapsed>false</primary-collapsed>
		<relation-collapsed>false</relation-collapsed>
		<basic-collapsed>false</basic-collapsed>
	</entity>
</entities>